[
    {
        "title": "Rara Mutton Recipe",
        "author": "NDTV Food",
        "description": "This Himachali dish is popularly enjoyed during special events and festive occasions. Prepared with a m\u00e9lange of classic Indian spices, this soulful red mutton curry shall make your mouth water.",
        "photo_url": "https://i.ndtvimg.com/i/2018-04/mutton-curry_620x330_81522907052.jpg",
        "servings": 4,
        "prep_time": "25 mins",
        "cook_time": "30 mins",
        "recipe_directions": {
            "1": "To begin making the Himachali Mutton Rara recipe, In a wide pan, dry roast all the garam masala ingredients except the nutmeg and grind them into a powder using a mixer grinder",
            "2": "Mix nutmeg powder in this mixture and keep it aside. Heat mustard oil in a heavy bottomed pan to smoking point and cumin seeds",
            "3": "Add chopped onion, green chillies, garlic and ginger and saute for 10 minutes",
            "4": "Add red chilli powder, turmeric powder and mix it properly. Add tomatoes,salt and sugar",
            "5": "Let it cook for 15 to 20 minutes on medium flame till tomatoes are soft and the oil has risen to the top. Sprinkle little water. Now mix mutton and let it cook for 20 to 25 minutes till it is rich and fully coated with all spices",
            "6": "Add ghee for the flavours. Cover the pan with a lid and let the mutton cook in its own juices for about 30 to 45 minutes",
            "7": "Half way through, sprinkle 1 big tablespoon freshly grounded garam masala. Once the mutton is tender, add some chopped coriander, lime juice and serve hot",
            "8": "Serve Himachali Mutton Rara along with hot steamed"
        },
        "recipe_ingredients": [
            {
                "quantity": "1",
                "unit_name": "kg",
                "name": "Mutton",
                "category": ""
            },
            {
                "quantity": "4",
                "unit_name": "tbsp",
                "name": "Mustard Oil",
                "category": ""
            },
            {
                "quantity": "1",
                "unit_name": "tbsp",
                "name": "Cumin seeds (Jeera)",
                "category": ""
            },
            {
                "quantity": "3",
                "unit_name": "",
                "name": "Onions, sliced",
                "category": ""
            },
            {
                "quantity": "2",
                "unit_name": "tbsp",
                "name": "Garlic (finely chopped)",
                "category": ""
            },
            {
                "quantity": "2",
                "unit_name": "tbsp",
                "name": "Ginger (finely chopped)",
                "category": ""
            },
            {
                "quantity": "1",
                "unit_name": "tbsp",
                "name": "Turmeric powder (Haldi)",
                "category": ""
            },
            {
                "quantity": "2",
                "unit_name": "tbsp",
                "name": "Red Chilli powder",
                "category": ""
            },
            {
                "quantity": "2",
                "unit_name": "",
                "name": "Green Chillies , chopped",
                "category": ""
            },
            {
                "quantity": "3",
                "unit_name": "",
                "name": "Tomatoes , finely chopped",
                "category": ""
            },
            {
                "quantity": "2",
                "unit_name": "tbsp",
                "name": "Ghee",
                "category": ""
            },
            {
                "quantity": "1",
                "unit_name": "tbsp",
                "name": "Lemon juice",
                "category": ""
            },
            {
                "name": "Coriander (Dhania) Leaves , Few sprigs, finely chopped",
                "unit_name": "",
                "quantity": "",
                "category": ""
            },
            {
                "name": "A pinch of Sugar",
                "unit_name": "",
                "quantity": "",
                "category": ""
            },
            {
                "name": "to taste Salt",
                "unit_name": "",
                "quantity": "",
                "category": ""
            },
            {
                "name": "For Garam masala",
                "unit_name": "",
                "quantity": "",
                "category": ""
            },
            {
                "quantity": "2",
                "unit_name": "",
                "name": "Mace (Javitri)",
                "category": ""
            },
            {
                "quantity": "5",
                "unit_name": "",
                "name": "Cloves",
                "category": ""
            },
            {
                "quantity": "1",
                "unit_name": "inch",
                "name": " Cinnamon Stick (Dalchini)",
                "category": ""
            },
            {
                "quantity": "1",
                "unit_name": "",
                "name": "Bay Leaf",
                "category": ""
            },
            {
                "quantity": "3",
                "unit_name": "",
                "name": "Cardamom (Elaichi) Pods/Seeds",
                "category": ""
            },
            {
                "quantity": "1",
                "unit_name": "tbsp",
                "name": "Coriander (Dhania) Seeds",
                "category": ""
            },
            {
                "quantity": "1",
                "unit_name": "tbsp",
                "name": "Cumin seeds (Jeera)",
                "category": ""
            },
            {
                "quantity": "1",
                "unit_name": "tbsp",
                "name": "Nutmeg (grated)",
                "category": ""
            }
        ],
        "recipe_cuisine": "Indian",
        "recipe_courses": [
            "Main Dish"
        ],
        "recipe_specialdiets": [
            "Non-Vegetarian"
        ]
    },
    {
        "title": "Mutton Akbari Recipe",
        "author": "NDTV Food",
        "description": "Mutton Akbari Recipe: Mutton Akbari is a delicious mutton curry and you can make curry for lavish dinner.Total Cook Time 25 mins Prep Time 10 mins Cook Time 15 mins Recipe Servings2EasyIngredients of Mutton Akbari1 Tbsp Ghee  1 tbsp Oil Salt (as required)500 gram Mutton (cooked)1 tbsp Ginger-Garlic Paste2  Tomatoes 3  Green Chillies 3 tbsp Curd  1/2 tsp Turmeric Powder 1 tsp Chaat Masala Powder 1 tsp Black Pepper Powder 1 tsp Red Chilli Powder 1 tsp Garam Masala Powder1 tsp Red Chilli Flakes Water (as required)  Lemon JuiceHow to Make Mutton AkbariHideShow \n                                            Media\n                                        1.Heat ghee in a pan, add boiled mutton, ginger garlic paste and season it with salt.  Fry the mutton till it brown.2.Add chopped tomatoes and green chilles. Once the tomatoes are nice and mushy, pour in the curd. keep stirring the curd to prevent it from curdling.3.Next, add turmeric powder, chat masala, pepper powder, red chilli powder, garam masala and red chillies flakes.4.Pour water and lemon juice. Cover the pan, once the gravy is combined, the dish is ready!Key Ingredients: Ghee  , Oil Salt (as required), Mutton (cooked), Ginger-Garlic Paste, Tomatoes , Green Chillies , Curd  , Turmeric Powder , Chaat Masala Powder , Black Pepper Powder , Red Chilli Powder , Garam Masala Powder, Red Chilli Flakes Water (as required), Lemon Juice\n                                        Tags:\n                                    MuttonAkbari5 Share Recipe Share Recipe Facebook\n                 Twitter\n                 Reddit\n                 \n                    Snapchat",
        "photo_url": "https://c.ndtvimg.com/2021-02/6tkrhcsg_mutton-curry_625x300_10_February_21.jpg",
        "servings": 2,
        "prep_time": "10 mins",
        "cook_time": "15 mins",
        "recipe_directions": {
            "1": "Heat ghee in a pan, add boiled mutton, ginger garlic paste and season it with salt.  Fry the mutton till it brown",
            "2": "Add chopped tomatoes and green chilles. Once the tomatoes are nice and mushy, pour in the curd. keep stirring the curd to prevent it from curdling",
            "3": "Next, add turmeric powder, chat masala, pepper powder, red chilli powder, garam masala and red chillies flakes",
            "4": "Pour water and lemon juice. Cover the pan, once the gravy is combined, the dish is ready!"
        },
        "recipe_ingredients": [
            {
                "quantity": "1",
                "unit_name": "tbsp",
                "name": "Ghee",
                "category": ""
            },
            {
                "quantity": "1",
                "unit_name": "tbsp",
                "name": "Oil Salt (as required)",
                "category": ""
            },
            {
                "quantity": "500",
                "unit_name": "gram",
                "name": "Mutton (cooked)",
                "category": ""
            },
            {
                "quantity": "1",
                "unit_name": "tbsp",
                "name": "Ginger-Garlic Paste",
                "category": ""
            },
            {
                "quantity": "2",
                "unit_name": "",
                "name": "Tomatoes",
                "category": ""
            },
            {
                "quantity": "3",
                "unit_name": "",
                "name": "Green Chillies",
                "category": ""
            },
            {
                "quantity": "3",
                "unit_name": "tbsp",
                "name": "Curd",
                "category": ""
            },
            {
                "quantity": "1/2",
                "unit_name": "tsp",
                "name": "Turmeric Powder",
                "category": ""
            },
            {
                "quantity": "1",
                "unit_name": "tsp",
                "name": "Chaat Masala Powder",
                "category": ""
            },
            {
                "quantity": "1",
                "unit_name": "tsp",
                "name": "Black Pepper Powder",
                "category": ""
            },
            {
                "quantity": "1",
                "unit_name": "tsp",
                "name": "Red Chilli Powder",
                "category": ""
            },
            {
                "quantity": "1",
                "unit_name": "tsp",
                "name": "Garam Masala Powder",
                "category": ""
            },
            {
                "quantity": "1",
                "unit_name": "tsp",
                "name": "Red Chilli Flakes Water (as required)",
                "category": ""
            },
            {
                "name": "Lemon Juice",
                "unit_name": "",
                "quantity": "",
                "category": ""
            }
        ],
        "recipe_cuisine": "Indian",
        "recipe_courses": [
            "Main Dish"
        ],
        "recipe_specialdiets": [
            "Non-Vegetarian"
        ]
    },
    {
        "title": "Badam Gosht Korma Recipe",
        "author": "NDTV Food",
        "description": "Badam Gosht Korma  Recipe: This is a delicious curry which is made by almond, curd and whole spices. This curry is perfect for your next dinner party.Total Cook Time1 hr  Prep Time 15 mins Cook Time 45 mins Recipe Servings2EasyIngredients of Badam Gosht Korma1/2 Kg mutton1 cups almonds2 large onions chopped and fried crisp 4 tbsp curd4 tbsp ghee1 tbsp ginger-garlic paste 1 tbsp coriander powder1 tbsp red chili powder 1/2 tsp turmeric powder  Salt as required1  cinnamon stick2  bay leaves 4-5  green cardamom 1  black cardamom 3-4 drops   kewra/rose waterHow to Make Badam Gosht KormaHideShow \n                                            Media\n                                        1.Wash and soak almonds in hot water for 10 minutes. Peel off the skin and take half the almonds and curd and make a fine paste. Keep it aside.2.In a pan add ghee and whole spices, once they start to splutter, add mutton and fry until the mutton has changed color.3.Now add ginger garlic paste and cook until the raw smell is gone.4.Once the ginger-garlic paste and mutton has mixed well, add coriander, cumin, red chili and turmeric powder, salt and mix well.5.After around 2 mins add the curd and almonds paste and cook until the masala starts leaving oil.6.Next add the crushed fried onions and mix well for some time. Once the masala looks cooked, add around 2cups water and leave it to simmer for almost 30 minutes in medium fame with the lid on.7.Check once if the mutton pieces are soft. Now add the remaining almonds and cook for 2 more minutes. End with adding either kewra or rose water and let it sit with the lid on for 2 minutes.8.Garnish with coriander leaves and serve hot.Key Ingredients: mutton, almonds, onions chopped and fried crisp , curd, ghee, ginger-garlic paste , coriander powder, red chili powder , turmeric powder, Salt as required, cinnamon stick, bay leaves , green cardamom , black cardamom ,  kewra/rose water\n                                        Tags:\n                                    BadamKorma5 Share Recipe Share Recipe Facebook\n                 Twitter\n                 Reddit\n                 \n                    Snapchat",
        "photo_url": "https://c.ndtvimg.com/2020-05/hmk1s0t_gosht_625x300_07_May_20.jpg",
        "servings": 2,
        "prep_time": "15 mins",
        "cook_time": "45 mins",
        "recipe_directions": {
            "1": "Wash and soak almonds in hot water for 10 minutes. Peel off the skin and take half the almonds and curd and make a fine paste. Keep it aside",
            "2": "In a pan add ghee and whole spices, once they start to splutter, add mutton and fry until the mutton has changed color",
            "3": "Now add ginger garlic paste and cook until the raw smell is gone",
            "4": "Once the ginger-garlic paste and mutton has mixed well, add coriander, cumin, red chili and turmeric powder, salt and mix well",
            "5": "After around 2 mins add the curd and almonds paste and cook until the masala starts leaving oil",
            "6": "Next add the crushed fried onions and mix well for some time. Once the masala looks cooked, add around 2cups water and leave it to simmer for almost 30 minutes in medium fame with the lid on",
            "7": "Check once if the mutton pieces are soft. Now add the remaining almonds and cook for 2 more minutes. End with adding either kewra or rose water and let it sit with the lid on for 2 minutes",
            "8": "Garnish with coriander leaves and serve hot"
        },
        "recipe_ingredients": [
            {
                "quantity": "1/2",
                "unit_name": "kg",
                "name": "mutton",
                "category": ""
            },
            {
                "quantity": "1",
                "unit_name": "cups",
                "name": "almonds",
                "category": ""
            },
            {
                "quantity": "2",
                "unit_name": "",
                "name": "large onions chopped and fried crisp",
                "category": ""
            },
            {
                "quantity": "4",
                "unit_name": "tbsp",
                "name": "curd",
                "category": ""
            },
            {
                "quantity": "4",
                "unit_name": "tbsp",
                "name": "ghee",
                "category": ""
            },
            {
                "quantity": "1",
                "unit_name": "tbsp",
                "name": "ginger-garlic paste",
                "category": ""
            },
            {
                "quantity": "1",
                "unit_name": "tbsp",
                "name": "coriander powder",
                "category": ""
            },
            {
                "quantity": "1",
                "unit_name": "tbsp",
                "name": "red chili powder",
                "category": ""
            },
            {
                "quantity": "1/2",
                "unit_name": "tsp",
                "name": "turmeric powder",
                "category": ""
            },
            {
                "name": "Salt as required",
                "unit_name": "",
                "quantity": "",
                "category": ""
            },
            {
                "quantity": "1",
                "unit_name": "",
                "name": "cinnamon stick",
                "category": ""
            },
            {
                "quantity": "2",
                "unit_name": "",
                "name": "bay leaves",
                "category": ""
            },
            {
                "quantity": "4",
                "unit_name": "",
                "name": "green cardamom",
                "category": ""
            },
            {
                "quantity": "1",
                "unit_name": "",
                "name": "black cardamom",
                "category": ""
            },
            {
                "quantity": "3",
                "unit_name": "drops",
                "name": "  kewra/rose water",
                "category": ""
            }
        ],
        "recipe_cuisine": "Indian",
        "recipe_courses": [
            "Main Dish"
        ],
        "recipe_specialdiets": [
            "Non-Vegetarian"
        ]
    },
    {
        "title": "Saag Gosht Recipe",
        "author": "Harangad Singh",
        "description": "Saag Gosht is lip-smacking curry of juicy and succulent mutton pieces cooked with coarsely pureed spinach and some aromatic spices. It is best served with chapati, naan or even tandoori roti. You can also pair it up with rice.",
        "photo_url": "https://c.ndtvimg.com/2022-01/qft28v6g_saag-gosht_625x300_13_January_22.jpg",
        "servings": 2,
        "prep_time": "15 mins",
        "cook_time": "25 mins",
        "recipe_directions": {
            "1": "Heat three tablespoons olive oil in a pan, add ginger, garlic and onion and saut\u00e9 for two to three minutes",
            "2": "Add mutton pieces and cook it for 3-4 mins or till the meat will be seared then add roughly chop mustard leaves",
            "3": "Cover and cook it till mutton gets tender",
            "4": "Add roughly chop spinach and stir",
            "5": "Add chopped green chillies. Add salt to taste and stir well",
            "6": "Ready to serve!"
        },
        "recipe_ingredients": [
            {
                "quantity": "5",
                "unit_name": "",
                "name": "Bunches  Fresh mustard leaves (sarson)",
                "category": ""
            },
            {
                "quantity": "1",
                "unit_name": "",
                "name": "Bunch  Fresh spinach leaves (palak)",
                "category": ""
            },
            {
                "quantity": "5",
                "unit_name": "tbsp",
                "name": "Olive oil",
                "category": ""
            },
            {
                "quantity": "2",
                "unit_name": "",
                "name": "one-inch pieces  Ginger sliced",
                "category": ""
            },
            {
                "quantity": "6",
                "unit_name": "",
                "name": "Cloves  Garlic sliced",
                "category": ""
            },
            {
                "quantity": "2",
                "unit_name": "",
                "name": "medium Onions Sliced",
                "category": ""
            },
            {
                "quantity": "4",
                "unit_name": "",
                "name": "Green Chillies",
                "category": ""
            },
            {
                "name": "Salt to taste",
                "unit_name": "",
                "quantity": "",
                "category": ""
            },
            {
                "quantity": "2",
                "unit_name": "tbsp",
                "name": "Cornmeal",
                "category": ""
            },
            {
                "quantity": "300",
                "unit_name": "gram",
                "name": "Mutton curry-cut",
                "category": ""
            }
        ],
        "recipe_cuisine": "Indian",
        "recipe_courses": [
            "Main Dish"
        ],
        "recipe_specialdiets": [
            "Non-Vegetarian"
        ]
    },
    {
        "title": "Lahori Mutton Karahi Recipe",
        "author": "NDTV Food",
        "description": "Made in a thick gravy of tomato and onions, the dish is perfect to pair with some rich buttery naan or parathas.",
        "photo_url": "https://c.ndtvimg.com/rglsbgh_mutton-roganjosh_625x300_17_August_18.jpg",
        "servings": 2,
        "prep_time": "15 mins",
        "cook_time": "30 mins",
        "recipe_directions": {
            "1": "Wash and dry mutton chunks, add garlic paste and let it sit for some time",
            "2": "In a karahi, heat oil and add cinnamon stick and cloves. Next add the mutton and fry for around 10 mins or until the colour has changed. Add ginger paste and chillies and keep frying",
            "3": "Add coriander powder, red chilli powder and haldi, some salt and keep frying",
            "4": "After the mutton is slightly cooked, add in the mix of tomato and onion puree and mix well. Keep cooking until the masala leaves oil",
            "5": "Now add some water and cover and cook until soft and tender. Check for salt and adjust accordingly",
            "6": "Take off the heat, garnish with ginger juliennes and serve hot"
        },
        "recipe_ingredients": [
            {
                "quantity": "750",
                "unit_name": "gms",
                "name": "Boneless Mutton",
                "category": ""
            },
            {
                "quantity": "1/2",
                "unit_name": "cup",
                "name": "Oil",
                "category": ""
            },
            {
                "quantity": "2",
                "unit_name": "",
                "name": "medium Tomatoes Puree",
                "category": ""
            },
            {
                "quantity": "1",
                "unit_name": "",
                "name": "small Onion Puree",
                "category": ""
            },
            {
                "quantity": "1",
                "unit_name": "tbsp",
                "name": "Ginger Paste",
                "category": ""
            },
            {
                "quantity": "1",
                "unit_name": "tsp",
                "name": "Garlic Paste",
                "category": ""
            },
            {
                "quantity": "3",
                "unit_name": "",
                "name": "Green Chillies (Slit)",
                "category": ""
            },
            {
                "quantity": "1",
                "unit_name": "inch",
                "name": " Cinnamon Stick",
                "category": ""
            },
            {
                "quantity": "2",
                "unit_name": "",
                "name": "Cloves",
                "category": ""
            },
            {
                "quantity": "1",
                "unit_name": "tsp",
                "name": "Coriander Powder",
                "category": ""
            },
            {
                "quantity": "1/2",
                "unit_name": "tsp",
                "name": "Red Chilli Powder",
                "category": ""
            },
            {
                "quantity": "1/2",
                "unit_name": "tsp",
                "name": "Haldi",
                "category": ""
            },
            {
                "name": "Salt according to taste",
                "unit_name": "",
                "quantity": "",
                "category": ""
            }
        ],
        "recipe_cuisine": "Indian",
        "recipe_courses": [
            "Main Dish"
        ],
        "recipe_specialdiets": [
            "Non-Vegetarian"
        ]
    },
    {
        "title": "Keto Butter Chicken Recipe",
        "author": "Dr Shunmukha Priya",
        "description": "About keto butter chicken : This keto friendly butter chicken recipe is just the right thing if you want something healthy yet delicious. Here creamy gravy is subtly laced with chicken chunks and desi spices.",
        "photo_url": "https://c.ndtvimg.com/2021-05/1459bjp8_keto-butter-chicken_625x300_13_May_21.jpg",
        "servings": 2,
        "prep_time": "15 mins",
        "cook_time": "10 mins",
        "recipe_directions": {
            "1": "In a bowl add turmeric Powder, Chilli Powder, Coriander powder and mix well",
            "2": "Marinate the chicken in this powder and keep for 15 mins",
            "3": "In a pan, heat the avocado oil, once it's hot, pan fry the chicken for 5 minutes on both sides till it gets fully cooked",
            "4": "In a pan, heat the butter and on melting, add tomato puree and mix well. Add kasuri methi, water and cover with a lid and cook for 5 minutes",
            "5": "Once tomato puree and oil get split, add heavy cream to this and mix well till everything has emulsified",
            "6": "Add the prepared chicken to this, add pepper powder and salt, mix well and cover for a min on a low flame",
            "7": "Garnish with chopped coriander leaves and serve with Rice /Roti"
        },
        "recipe_ingredients": [
            {
                "quantity": "200",
                "unit_name": "gms",
                "name": "Boneless & Skinless Chicken",
                "category": ""
            },
            {
                "quantity": "10",
                "unit_name": "gram",
                "name": "Butter",
                "category": ""
            },
            {
                "quantity": "1",
                "unit_name": "tsp",
                "name": "Kasuri Methi",
                "category": ""
            },
            {
                "quantity": "100",
                "unit_name": "ml",
                "name": "Tomato Puree",
                "category": ""
            },
            {
                "quantity": "50",
                "unit_name": "ml",
                "name": "Heavy Cream",
                "category": ""
            },
            {
                "quantity": "1",
                "unit_name": "tsp",
                "name": "Avocado Oil",
                "category": ""
            },
            {
                "quantity": "50",
                "unit_name": "ml",
                "name": "Water",
                "category": ""
            },
            {
                "quantity": "1/2",
                "unit_name": "tsp",
                "name": "Turmeric Powder",
                "category": ""
            },
            {
                "quantity": "1/2",
                "unit_name": "tsp",
                "name": "Chilli Powder",
                "category": ""
            },
            {
                "quantity": "1/4",
                "unit_name": "tsp",
                "name": "Pepper Powder",
                "category": ""
            },
            {
                "quantity": "1/2",
                "unit_name": "tsp",
                "name": "Coriander powder",
                "category": ""
            },
            {
                "name": "to taste Salt",
                "unit_name": "",
                "quantity": "",
                "category": ""
            },
            {
                "quantity": "2",
                "unit_name": "tsp",
                "name": "Chopped coriander leaves",
                "category": ""
            }
        ],
        "recipe_cuisine": "Indian",
        "recipe_courses": [
            "Main Dish"
        ],
        "recipe_specialdiets": [
            "Non-Vegetarian"
        ]
    },
    {
        "title": "Nilgiri Turkey Korma Recipe",
        "author": "",
        "description": "About Nilgiri Turkey Korma Recipe: A luscious, creamy turkey korma, made with a melange of spices along with coconut paste and curd.This is a perfect dish to prepare for your next dinner party!",
        "photo_url": "https://c.ndtvimg.com/2020-07/9ouoj49_chicken_625x300_03_July_20.jpg",
        "servings": 2,
        "prep_time": "15 mins",
        "cook_time": "45 mins",
        "recipe_directions": {
            "1": "In a cooker, add turkey meat, salt, turmeric powder and water",
            "2": "Cover with lid and boil it allowing 2 whistles. When the turkey is boiled then put it aside",
            "3": "In a mixer jar, add spinach leaves, mint leaves, coriander leaves, green chilli, little water and grind it into a fine paste",
            "4": "In a pan, add oil, then add shahi jeera, chopped onions, ginger garlic paste, and fry for 5 minutes",
            "5": "Add boiled turkey meat pieces and mix well. Add fresh curry leaves and mix well. Cook for 10 minutes",
            "6": "After 10 minutes, add coconut paste and mix well. Oil will ooze out",
            "7": "Add curd, salt to taste, grounded spinach paste and mix well for 5 minutes. Fry until aromatic",
            "8": "Add 1 glass of water and mix well, then add coriander powder and mix again",
            "9": "Cover with lid to boil the turkey meat for 10 minutes",
            "10": "After 10 minutes, open the lid and stir well",
            "11": "When curry is almost done, add garam masala powder and stir. Add fresh coriander leaves, put in a serving bowl, and serve hot"
        },
        "recipe_ingredients": [
            {
                "quantity": "750",
                "unit_name": "gms",
                "name": "turkey meat",
                "category": ""
            },
            {
                "quantity": "100",
                "unit_name": "gms",
                "name": "spinach",
                "category": ""
            },
            {
                "quantity": "1",
                "unit_name": "",
                "name": "bunch mint leaves",
                "category": ""
            },
            {
                "quantity": "2",
                "unit_name": "",
                "name": "bunch coriander leaves",
                "category": ""
            },
            {
                "quantity": "10",
                "unit_name": "",
                "name": "Green chilli",
                "category": ""
            },
            {
                "quantity": "150",
                "unit_name": "gms",
                "name": "onions",
                "category": ""
            },
            {
                "quantity": "250",
                "unit_name": "gms",
                "name": "ginger-garlic paste",
                "category": ""
            },
            {
                "quantity": "1/2",
                "unit_name": "tsp",
                "name": "turmeric powder",
                "category": ""
            },
            {
                "quantity": "10",
                "unit_name": "gms",
                "name": "shahi jeera",
                "category": ""
            },
            {
                "quantity": "100",
                "unit_name": "gms",
                "name": "curd",
                "category": ""
            },
            {
                "quantity": "100",
                "unit_name": "gms",
                "name": "coconut paste",
                "category": ""
            },
            {
                "quantity": "1",
                "unit_name": "tbsp",
                "name": "coriander powder",
                "category": ""
            },
            {
                "quantity": "10",
                "unit_name": "gms",
                "name": "garam masala powder",
                "category": ""
            },
            {
                "quantity": "100",
                "unit_name": "ml",
                "name": "oil",
                "category": ""
            },
            {
                "name": "to taste salt",
                "unit_name": "",
                "quantity": "",
                "category": ""
            },
            {
                "name": "Water",
                "unit_name": "",
                "quantity": "",
                "category": ""
            }
        ],
        "recipe_cuisine": "Indian",
        "recipe_courses": [
            "Main Dish"
        ],
        "recipe_specialdiets": [
            "Non-Vegetarian"
        ]
    },
    {
        "title": "Laal Maas Recipe",
        "author": "Ashish Roy",
        "description": "About Laal Maas Recipe: Laal Maas is a Rajasthani dish, fiery as ever, that you simply shouldn't miss! Here's a laal maas recipe packed with red chillies that you can try at home.",
        "photo_url": "https://c.ndtvimg.com/2020-05/g8e7cqsg_laal-maas_625x300_27_May_20.jpg",
        "servings": 2,
        "prep_time": "1 hr 20 mins",
        "cook_time": "1 hr",
        "recipe_directions": {
            "1": "Heat oil in a non-stick pressure cooker, to that add black cardamom, green cardamoms, cinnamon, cloves, whole mathania (red chilli) and bay leaf and saut\u00e9 till its fragrant",
            "2": "Add the onions and saut\u00e9 till they turn light brown in colour. Then add the remaining ginger garlic paste and saut\u00e9 for 5 minutes",
            "3": "Add the lamb pieces to the onions and saut\u00e9 on high heat for 10-15 minutes until the meat is seared properly",
            "4": "Add turmeric powder, mathania (red chilly) paste, salt and saut\u00e9 for 10 minutes",
            "5": "Whisk the yoghurt and add into lamb and saut\u00e9 on medium flame for 10 minutes, then keep it on simmer (slow flame) and let the mutton cook slowly.  Add little water or stock if required at any stage. Adjust seasoning",
            "6": "Once the lamb is cooked, transfer to a serving bowl, garnish with coriander sprigs and a lemon wedge. Serve hot"
        },
        "recipe_ingredients": [
            {
                "quantity": "600",
                "unit_name": "gms",
                "name": "Mutton (cut into 1 inch pieces)",
                "category": ""
            },
            {
                "quantity": "3",
                "unit_name": "",
                "name": "Black cardamoms (crushed)",
                "category": ""
            },
            {
                "quantity": "4",
                "unit_name": "",
                "name": "Green cardamoms",
                "category": ""
            },
            {
                "quantity": "2",
                "unit_name": "tsp",
                "name": "cumin powder",
                "category": ""
            },
            {
                "quantity": "3",
                "unit_name": "",
                "name": "Cloves",
                "category": ""
            },
            {
                "quantity": "150",
                "unit_name": "ml",
                "name": "oil",
                "category": ""
            },
            {
                "quantity": "5",
                "unit_name": "",
                "name": "Mathania whole red chilly",
                "category": ""
            },
            {
                "quantity": "200",
                "unit_name": "gms",
                "name": "onions, sliced",
                "category": ""
            },
            {
                "quantity": "2",
                "unit_name": "tbsp",
                "name": "ginger-garlic paste",
                "category": ""
            },
            {
                "quantity": "1",
                "unit_name": "tsp",
                "name": "turmeric paste",
                "category": ""
            },
            {
                "quantity": "2",
                "unit_name": "tsp",
                "name": "Mathania (red chilli) paste",
                "category": ""
            },
            {
                "name": "to taste salt",
                "unit_name": "",
                "quantity": "",
                "category": ""
            },
            {
                "quantity": "200",
                "unit_name": "gms",
                "name": "yogurt",
                "category": ""
            },
            {
                "name": "for garnishing coriander sprig",
                "unit_name": "",
                "quantity": "",
                "category": ""
            },
            {
                "name": "for garnishing lemon wedges",
                "unit_name": "",
                "quantity": "",
                "category": ""
            },
            {
                "quantity": "1",
                "unit_name": "inch",
                "name": "stick  cinnamon",
                "category": ""
            },
            {
                "quantity": "1",
                "unit_name": "",
                "name": "Bay leaf",
                "category": ""
            }
        ],
        "recipe_cuisine": "Indian",
        "recipe_courses": [
            "Main Dish"
        ],
        "recipe_specialdiets": [
            "Non-Vegetarian"
        ]
    },
    {
        "title": "Lauki Gosht Recipe",
        "author": "Mohammed Nafeesh - Courtyard Bengaluru Outer Ring Road",
        "description": "A delicious combination of Lauki and Mutton comes alive in the form of this spicy, aromatic dish of Lauki Gosht.",
        "photo_url": "https://c.ndtvimg.com/lauki-gosht_625x300_1528974900919.jpg",
        "servings": 2,
        "prep_time": "10 mins",
        "cook_time": "40 mins",
        "recipe_directions": {
            "1": "Wash and peel the Lauki. Cut in to halves and wash and then keep a side",
            "2": "Heat oil in a wok and add cinnamon stick, black cardamom and finely chopped onions, fry onions till golden brown",
            "3": "Add the meat and saut\u00e9. Add ginger garlic paste and mix",
            "4": "Add coriander, turmeric, red chilli powder along with salt and fry all of these spices",
            "5": "Add chopped tomatoes and cook, followed by lauki and continue cooking with little water",
            "6": "Let it simmer until the mutton is cooked",
            "7": "Now add water depending on how thin you want the gravy",
            "8": "Serve garnished with fresh coriander leaves"
        },
        "recipe_ingredients": [
            {
                "quantity": "500",
                "unit_name": "gram",
                "name": "Mutton",
                "category": ""
            },
            {
                "quantity": "500",
                "unit_name": "gram",
                "name": "Lauki",
                "category": ""
            },
            {
                "quantity": "1",
                "unit_name": "tsp",
                "name": "Red chilli powder",
                "category": ""
            },
            {
                "quantity": "1/4",
                "unit_name": "tsp",
                "name": "Turmeric powder",
                "category": ""
            },
            {
                "quantity": "2",
                "unit_name": "tsp",
                "name": "Coriander powder",
                "category": ""
            },
            {
                "quantity": "1",
                "unit_name": "tsp",
                "name": "Garlic paste",
                "category": ""
            },
            {
                "quantity": "1",
                "unit_name": "tsp",
                "name": "Ginger paste",
                "category": ""
            },
            {
                "quantity": "3",
                "unit_name": "tbsp",
                "name": "Fresh coriander leaves",
                "category": ""
            },
            {
                "quantity": "2",
                "unit_name": "",
                "name": "Green chillies",
                "category": ""
            },
            {
                "quantity": "2",
                "unit_name": "",
                "name": "Tomatoes",
                "category": ""
            },
            {
                "quantity": "2",
                "unit_name": "",
                "name": "Onion",
                "category": ""
            },
            {
                "quantity": "1",
                "unit_name": "",
                "name": "Cinnamon stick",
                "category": ""
            },
            {
                "name": "To taste Salt",
                "unit_name": "",
                "quantity": "",
                "category": ""
            },
            {
                "quantity": "4",
                "unit_name": "tbsp",
                "name": "Oil",
                "category": ""
            },
            {
                "name": "For frying  OIl",
                "unit_name": "",
                "quantity": "",
                "category": ""
            }
        ],
        "recipe_cuisine": "Indian",
        "recipe_courses": [
            "Main Dish"
        ],
        "recipe_specialdiets": [
            "Non-Vegetarian"
        ]
    },
    {
        "title": "Steamed Fish In Banana Leaves Recipe",
        "author": "NDTV Food",
        "description": "If you love seafood, this recipe will definitely make you crazy.  Besides, it is easy-to-make, delicious and very apt for serving on occasions like birthdays, anniversaries, get-togethers and other parties.",
        "photo_url": "https://c.ndtvimg.com/2022-05/sp25ndi8_fish_625x300_30_May_22.jpg",
        "servings": 2,
        "prep_time": "05 mins",
        "cook_time": "15 mins",
        "recipe_directions": {
            "1": "We first need to marinate the fish. For this, take a bowl, add fish chunks, lemon juice and salt. Keep it aside for 10 mins atleast",
            "2": "Now, take a grinder, add coconut, coriander leaves, green chillies, garlic and cumin seeds to a fine paste",
            "3": "Once done, wash banana leaves and pat try them. Spread it on the kitchen\u2019s slab and put the marinated fish on top of it. Now spread the paste over it",
            "4": "Fold the banana leaves neatly and steam them in a steamer with plenty of hot water",
            "5": "Serve and enjoy!"
        },
        "recipe_ingredients": [
            {
                "quantity": "2",
                "unit_name": "",
                "name": "Fish Fillet",
                "category": ""
            },
            {
                "quantity": "2",
                "unit_name": "tbsp",
                "name": "Lemon Juice",
                "category": ""
            },
            {
                "name": "to taste Salt",
                "unit_name": "",
                "quantity": "",
                "category": ""
            },
            {
                "quantity": "2",
                "unit_name": "tbsp",
                "name": "Coriander Leaves",
                "category": ""
            },
            {
                "quantity": "4",
                "unit_name": "tbsp",
                "name": "Desiccated Coconut",
                "category": ""
            },
            {
                "quantity": "6",
                "unit_name": "",
                "name": "Green Chillies",
                "category": ""
            },
            {
                "quantity": "7",
                "unit_name": "",
                "name": "Garlic Cloves",
                "category": ""
            },
            {
                "quantity": "1",
                "unit_name": "tsp",
                "name": "Cumin Seeds",
                "category": ""
            },
            {
                "name": "Boiled Water As Required",
                "unit_name": "",
                "quantity": "",
                "category": ""
            }
        ],
        "recipe_cuisine": "Indian",
        "recipe_courses": [
            "Main Dish"
        ],
        "recipe_specialdiets": [
            "Non-Vegetarian"
        ]
    }
]